remove_ai_comments/__init__.py
remove_ai_comments/cli.py
remove_ai_comments-0.1.1.dist-info/licenses/LICENSE
remove_ai_comments-0.1.1.dist-info/METADATA
remove_ai_comments-0.1.1.dist-info/WHEEL
remove_ai_comments-0.1.1.dist-info/entry_points.txt
remove_ai_comments-0.1.1.dist-info/top_level.txt
remove_ai_comments-0.1.1.dist-info/RECORD
