Metadata-Version: 2.4
Name: remove-ai-comments
Version: 0.1.1
Summary: CLI for removing all comments from source files, which were generated by AI
Home-page: https://github.com/maslakovSaveliy/remove-ai-comments
Author: Saveliy Maslakov
Author-email: saveliymaslakov969@gmail.com
License: MIT
Project-URL: Source, https://github.com/maslakovSaveliy/remove-ai-comments
Project-URL: Tracker, https://github.com/maslakovSaveliy/remove-ai-comments/issues
Requires-Python: >=3.6
License-File: LICENSE
Dynamic: author
Dynamic: author-email
Dynamic: description
Dynamic: description-content-type
Dynamic: home-page
Dynamic: license
Dynamic: license-file
Dynamic: project-url
Dynamic: requires-python
Dynamic: summary
